analphipy/__init__.py
analphipy/_attrs_utils.py
analphipy/_docstrings.py
analphipy/_typing.py
analphipy/_typing_compat.py
analphipy/base_potential.py
analphipy/measures.py
analphipy/norofrenkel.py
analphipy/potential.py
analphipy/py.typed
analphipy/utils.py
analphipy-0.4.1.dist-info/METADATA
analphipy-0.4.1.dist-info/WHEEL
analphipy-0.4.1.dist-info/licenses/LICENSE
analphipy-0.4.1.dist-info/RECORD
