Metadata-Version: 2.4
Name: analphipy
Version: 0.4.1
Summary: Utilities to perform stat mech analysis of pair potentials
Project-URL: Documentation, https://pages.nist.gov/analphipy/
Project-URL: Homepage, https://github.com/usnistgov/analphipy
Author-email: "William P. Krekelberg" <wpk@nist.gov>
License: NIST-PD
License-File: LICENSE
Keywords: analphipy
Classifier: Development Status :: 2 - Pre-Alpha
Classifier: Intended Audience :: Science/Research
Classifier: License :: Public Domain
Classifier: Operating System :: OS Independent
Classifier: Programming Language :: Python
Classifier: Programming Language :: Python :: 3 :: Only
Classifier: Programming Language :: Python :: 3.8
Classifier: Programming Language :: Python :: 3.9
Classifier: Programming Language :: Python :: 3.10
Classifier: Programming Language :: Python :: 3.11
Classifier: Programming Language :: Python :: 3.12
Classifier: Programming Language :: Python :: 3.13
Classifier: Topic :: Scientific/Engineering
Requires-Python: <3.14,>=3.8
Requires-Dist: attrs
Requires-Dist: docstring-inheritance
Requires-Dist: module-utilities>=0.10.1
Requires-Dist: numpy
Requires-Dist: scipy
Requires-Dist: typing-extensions; python_version < '3.11'
Provides-Extra: viz
Requires-Dist: matplotlib; extra == 'viz'
Requires-Dist: pandas; extra == 'viz'
